AsyncRequests.py
RequestObject.py
RequestsType.py
__init__.py
helper.py
async_http_requests-0.7.1.dist-info/licenses/LICENSE
async_http_requests-0.7.1.dist-info/METADATA
async_http_requests-0.7.1.dist-info/WHEEL
async_http_requests-0.7.1.dist-info/top_level.txt
async_http_requests-0.7.1.dist-info/RECORD
