Metadata-Version: 2.4
Name: async-http-requests
Version: 0.7.1
Summary: Asynchronous HTTP requests
Author-email: Andrea Sergi <andrea.serg1@gmail.com>
License: MIT License
Project-URL: Homepage, https://github.com/sclash/AsyncRequests
Keywords: http,requests,api,asyncio
Classifier: License :: OSI Approved :: MIT License
Classifier: Programming Language :: Python
Classifier: Programming Language :: Python :: 3
Requires-Python: >=3.9
License-File: LICENSE
Requires-Dist: requests>=2.28.0
Requires-Dist: requests-oauthlib>=1.3.0
Requires-Dist: dataclasses>=0.6
Requires-Dist: tomli>=2.0.1; python_version < "3.11"
Requires-Dist: setuptools>=80.9.0
Requires-Dist: progressbar2>=4.5.0
Dynamic: license-file
